LICENSE
optical/__init__.py
optical/converter/__init__.py
optical/converter/base.py
optical/converter/coco.py
optical/converter/converter.py
optical/converter/createml.py
optical/converter/csv.py
optical/converter/pascal.py
optical/converter/sagemaker.py
optical/converter/simple_json.py
optical/converter/tfrecord.py
optical/converter/utils.py
optical/converter/yolo.py
optical/visualizer/__init__.py
optical/visualizer/config.py
optical/visualizer/utils.py
optical/visualizer/visualizer.py
optical-0.0.2.dist-info/LICENSE
optical-0.0.2.dist-info/WHEEL
optical-0.0.2.dist-info/METADATA
optical-0.0.2.dist-info/RECORD
